gameday-0.0.0.data/scripts/gd-util
gameday-0.0.0.dist-info/DESCRIPTION.rst
gameday-0.0.0.dist-info/METADATA
gameday-0.0.0.dist-info/metadata.json
gameday-0.0.0.dist-info/RECORD
gameday-0.0.0.dist-info/top_level.txt
gameday-0.0.0.dist-info/WHEEL
gd/__init__.py
gd/database.py
gd/models.py
gd/parser.py
gd/scrape.py
gd/storage.py
gd/utils.py
gd/scripts/__init__.py
gd/scripts/util.py
gd/tests/__init__.py
gd/tests/test_parser.py
gd/tests/test_scrape.py
gd/tests/test_utils.py
usr/local/etc/gd/db.conf.example
usr/local/etc/gd/storage.conf.example
