Metadata-Version: 2.0
Name: gameday
Version: 0.0.0
Summary: Tools for working with MLB's Gameday data
Home-page: UNKNOWN
Author: Brian Curtin
Author-email: brian@python.org
License: UNKNOWN
Platform: UNKNOWN
Classifier: Development Status :: 1 - Planning
Classifier: Intended Audience :: Developers
Classifier: License :: OSI Approved :: MIT License
Classifier: Programming Language :: Python :: 3
Classifier: Programming Language :: Python :: 3.4
Classifier: Programming Language :: Python :: 3 :: Only
Requires-Dist: requests
Requires-Dist: sqlalchemy
